dnt/__init__.py
dnt/analysis/__init__.py
dnt/analysis/count.py
dnt/analysis/interaction2.py
dnt/analysis/position.py
dnt/analysis/speed.py
dnt/analysis/stop.py
dnt/analysis/stop2.py
dnt/analysis/stop3.py
dnt/detect/__init__.py
dnt/detect/timestamp.py
dnt/detect/signal/detector.py
dnt/detect/yolov8/__init__.py
dnt/detect/yolov8/detector.py
dnt/detect/yolov8/segmentor.py
dnt/engine/__init__.py
dnt/engine/bbox_interp.py
dnt/engine/bbox_iou.py
dnt/engine/cluster.py
dnt/engine/iob.py
dnt/filter/__init__.py
dnt/filter/filter.py
dnt/label/__init__.py
dnt/label/labeler.py
dnt/label/labeler2.py
dnt/shared/__init__.py
dnt/shared/convert.py
dnt/shared/download.py
dnt/shared/files.py
dnt/shared/filter.py
dnt/shared/synhcro.py
dnt/shared/util.py
dnt/shared/data/coco.names
dnt/shared/data/openimages.names
dnt/shared/data/voc.names
dnt/third_party/fast-reid/__init__.py
dnt/third_party/fast-reid/fast_reid_interfece.py
dnt/third_party/fast-reid/checkpoint/__init__.py
dnt/third_party/fast-reid/configs/Base-AGW.yml
dnt/third_party/fast-reid/configs/Base-MGN.yml
dnt/third_party/fast-reid/configs/Base-SBS.yml
dnt/third_party/fast-reid/configs/Base-bagtricks.yml
dnt/third_party/fast-reid/configs/__init__.py
dnt/third_party/fast-reid/configs/DukeMTMC/AGW_R101-ibn.yml
dnt/third_party/fast-reid/configs/DukeMTMC/AGW_R50-ibn.yml
dnt/third_party/fast-reid/configs/DukeMTMC/AGW_R50.yml
dnt/third_party/fast-reid/configs/DukeMTMC/AGW_S50.yml
dnt/third_party/fast-reid/configs/DukeMTMC/bagtricks_R101-ibn.yml
dnt/third_party/fast-reid/configs/DukeMTMC/bagtricks_R50-ibn.yml
dnt/third_party/fast-reid/configs/DukeMTMC/bagtricks_R50.yml
dnt/third_party/fast-reid/configs/DukeMTMC/bagtricks_S50.yml
dnt/third_party/fast-reid/configs/DukeMTMC/mgn_R50-ibn.yml
dnt/third_party/fast-reid/configs/DukeMTMC/sbs_R101-ibn.yml
dnt/third_party/fast-reid/configs/DukeMTMC/sbs_R50-ibn.yml
dnt/third_party/fast-reid/configs/DukeMTMC/sbs_R50.yml
dnt/third_party/fast-reid/configs/DukeMTMC/sbs_S50.yml
dnt-0.3.1.8.dist-info/licenses/LICENSE
dnt-0.3.1.8.dist-info/METADATA
dnt-0.3.1.8.dist-info/WHEEL
dnt-0.3.1.8.dist-info/top_level.txt
dnt-0.3.1.8.dist-info/RECORD
