Metadata-Version: 2.4
Name: dnt
Version: 0.3.1.8
Summary: A Python tool for video-based traffic analytiscs
Home-page: https://its.cutr.usf.edu/dnt/
Author: Zhenyu Wang
Author-email: wonstran@hotmail.com
License: MIT
Keywords: traffic,vehicle,trajectory,safety
Classifier: Development Status :: 3 - Alpha
Classifier: Intended Audience :: End Users/Desktop
Classifier: License :: OSI Approved :: MIT License
Classifier: Programming Language :: Python :: 3
Requires-Python: >=3.9
License-File: LICENSE
Requires-Dist: torch
Requires-Dist: torchvision
Requires-Dist: torchaudio
Requires-Dist: ultralytics>=8.2
Requires-Dist: cython
Requires-Dist: cython_bbox
Requires-Dist: easydict
Requires-Dist: faiss-cpu
Requires-Dist: faiss-gpu-cu12
Requires-Dist: filterpy
Requires-Dist: gdown
Requires-Dist: geopandas
Requires-Dist: h5py
Requires-Dist: lapx
Requires-Dist: loguru
Requires-Dist: matplotlib
Requires-Dist: motmetrics
Requires-Dist: ninja
Requires-Dist: numpy
Requires-Dist: numpy_indexed
Requires-Dist: opencv-contrib-python
Requires-Dist: opencv-python
Requires-Dist: pandas
Requires-Dist: Pillow
Requires-Dist: prettytable
Requires-Dist: pycocotools
Requires-Dist: pyyaml
Requires-Dist: scikit-image
Requires-Dist: scikit-learn
Requires-Dist: scipy
Requires-Dist: shapely
Requires-Dist: sympy
Requires-Dist: tabulate
Requires-Dist: tensorboard
Requires-Dist: termcolor
Requires-Dist: thop
Requires-Dist: tqdm
Requires-Dist: vidgear
Requires-Dist: yacs
Dynamic: author
Dynamic: author-email
Dynamic: classifier
Dynamic: description
Dynamic: description-content-type
Dynamic: home-page
Dynamic: keywords
Dynamic: license
Dynamic: license-file
Dynamic: requires-dist
Dynamic: requires-python
Dynamic: summary
